Metadata-Version: 1.0
Name: marcusdb
Version: 1.0.2
Summary: A python library for https://db.marcusweinberger.repl.co/
Home-page: https://github.com/AgeOfMarcus/mdb
Author: AgeOfMarcus
Author-email: marcus@marcusweinberger.com
License: UNKNOWN
Platform: UNKNOWN
